jupyterlite_xeus_wren/__init__.py
jupyterlite_xeus_wren/_version.py
jupyterlite_xeus_wren/labextension/package.json
jupyterlite_xeus_wren/labextension/static/213.8eb0b57fb5f20ee0423f.js
jupyterlite_xeus_wren/labextension/static/234.f0391790f78105d70e05.js
jupyterlite_xeus_wren/labextension/static/4ea3d9de762deaea46a97f7b86a042e61b508d5151738178694da40d75a4479a.png
jupyterlite_xeus_wren/labextension/static/747.7c59d9ca8f9202d24d4a.js
jupyterlite_xeus_wren/labextension/static/814862bbbed93fb113fe365e92ce092bb9caaf2d8699dff76004ae353f3a4b1d.png
jupyterlite_xeus_wren/labextension/static/remoteEntry.6e7c2ba8038680301a15.js
jupyterlite_xeus_wren/labextension/static/style.js
jupyterlite_xeus_wren/labextension/static/third-party-licenses.json
jupyterlite_xeus_wren/labextension/static/xeus_kernel.wasm
jupyterlite_xeus_wren-0.2.1.data/data/share/jupyter/labextensions/jupyterlite-xeus-wren/install.json
jupyterlite_xeus_wren-0.2.1.data/data/share/jupyter/labextensions/jupyterlite-xeus-wren/package.json
jupyterlite_xeus_wren-0.2.1.data/data/share/jupyter/labextensions/jupyterlite-xeus-wren/static/213.8eb0b57fb5f20ee0423f.js
jupyterlite_xeus_wren-0.2.1.data/data/share/jupyter/labextensions/jupyterlite-xeus-wren/static/234.f0391790f78105d70e05.js
jupyterlite_xeus_wren-0.2.1.data/data/share/jupyter/labextensions/jupyterlite-xeus-wren/static/4ea3d9de762deaea46a97f7b86a042e61b508d5151738178694da40d75a4479a.png
jupyterlite_xeus_wren-0.2.1.data/data/share/jupyter/labextensions/jupyterlite-xeus-wren/static/747.7c59d9ca8f9202d24d4a.js
jupyterlite_xeus_wren-0.2.1.data/data/share/jupyter/labextensions/jupyterlite-xeus-wren/static/814862bbbed93fb113fe365e92ce092bb9caaf2d8699dff76004ae353f3a4b1d.png
jupyterlite_xeus_wren-0.2.1.data/data/share/jupyter/labextensions/jupyterlite-xeus-wren/static/remoteEntry.6e7c2ba8038680301a15.js
jupyterlite_xeus_wren-0.2.1.data/data/share/jupyter/labextensions/jupyterlite-xeus-wren/static/style.js
jupyterlite_xeus_wren-0.2.1.dist-info/LICENSE
jupyterlite_xeus_wren-0.2.1.dist-info/METADATA
jupyterlite_xeus_wren-0.2.1.dist-info/WHEEL
jupyterlite_xeus_wren-0.2.1.dist-info/top_level.txt
jupyterlite_xeus_wren-0.2.1.dist-info/RECORD
